simple_icd_10/__init__.py
simple_icd_10/simple_icd_10.py
simple_icd_10/data/__init__.py
simple_icd_10/data/icd_10_v2019.xml
simple_icd_10-2.1.0.dist-info/LICENSE
simple_icd_10-2.1.0.dist-info/METADATA
simple_icd_10-2.1.0.dist-info/WHEEL
simple_icd_10-2.1.0.dist-info/top_level.txt
simple_icd_10-2.1.0.dist-info/RECORD
