Metadata-Version: 2.1
Name: simple_icd_10
Version: 2.1.0
Summary: A simple python library for ICD-10 codes
Home-page: https://github.com/StefanoTrv/simple_icd_10
Author: Stefano Travasci
Author-email: stefanotravasci@gmail.com
Keywords: ICD-10 icd 10 codes
Classifier: Programming Language :: Python :: 3
Classifier: License :: CC0 1.0 Universal (CC0 1.0) Public Domain Dedication
Classifier: Operating System :: OS Independent
Requires-Python: >=3.9
License-File: LICENSE
